AutoDockTools/AutoDockBondClassifier.py
AutoDockTools/AutoLigand.py
AutoDockTools/AutoLigandCommand.py
AutoDockTools/ConfPlayer.py
AutoDockTools/Conformation.py
AutoDockTools/DlgFilters.py
AutoDockTools/DlgParser.py
AutoDockTools/Docking.py
AutoDockTools/DockingFilters.py
AutoDockTools/DockingParameters.py
AutoDockTools/EntropiaParser.py
AutoDockTools/EpdbParser.py
AutoDockTools/GridParameters.py
AutoDockTools/InteractionDetector.py
AutoDockTools/LigandMixin.py
AutoDockTools/MoleculePreparation.py
AutoDockTools/ResultParser.py
AutoDockTools/TrajParser.py
AutoDockTools/VSResultFilters.py
AutoDockTools/WebServices.py
AutoDockTools/XMLParser.py
AutoDockTools/__init__.py
AutoDockTools/adthosts.py
AutoDockTools/atomTypeTools.py
AutoDockTools/autoanalyze3Commands.py
AutoDockTools/autoanalyze41Commands.py
AutoDockTools/autoanalyze4Commands.py
AutoDockTools/autoanalyzeCommands.py
AutoDockTools/autodockHosts.py
AutoDockTools/autodpf3Commands.py
AutoDockTools/autodpf41Commands.py
AutoDockTools/autodpf4Commands.py
AutoDockTools/autodpfCommands.py
AutoDockTools/autoflex41Commands.py
AutoDockTools/autoflex4Commands.py
AutoDockTools/autoflexCommands.py
AutoDockTools/autogpf3Commands.py
AutoDockTools/autogpf41Commands.py
AutoDockTools/autogpf4Commands.py
AutoDockTools/autogpfCommands.py
AutoDockTools/autopilotCommands.py
AutoDockTools/autostart3Commands.py
AutoDockTools/autostart41Commands.py
AutoDockTools/autostart4Commands.py
AutoDockTools/autostartCommands.py
AutoDockTools/autotors3Commands.py
AutoDockTools/autotors41Commands.py
AutoDockTools/autotors4Commands.py
AutoDockTools/autotorsCommands.py
AutoDockTools/cluster.py
AutoDockTools/cluster_ad.py
AutoDockTools/cmdlib.py
AutoDockTools/energyCalculator.py
AutoDockTools/energyConstants.py
AutoDockTools/filterLigands.py
AutoDockTools/histogram.py
AutoDockTools/interactiveHistogramGraph.py
AutoDockTools/lib_parameter_file_writer.py
AutoDockTools/modlib.py
AutoDockTools/pixelMap2D.py
AutoDockTools/pyAutoDockCommands.py
docking_tools_amw-0.4.0.dist-info/METADATA
docking_tools_amw-0.4.0.dist-info/WHEEL
docking_tools_amw-0.4.0.dist-info/top_level.txt
docking_tools_amw-0.4.0.dist-info/zip-safe
docking_tools_amw-0.4.0.dist-info/RECORD
